{
  "contacts": [
    {
      "fullname": "عادل",
      "photo": "https://avatar.iran.liara.run/public/5",
      "mobile": "091325468415",
      "email": "adelnouri0231@gmail.com",
      "job": "web developer",
      "group": "2",
      "id": 3
    },
    {
      "fullname": "محمدرضا نوری",
      "photo": "https://avatar.iran.liara.run/public/1",
      "mobile": "09132554186",
      "email": "mohammadreza@gmail.com",
      "job": "کارمند",
      "group": "3",
      "id": 4
    },
    {
      "fullname": "dafa",
      "photo": "https://avatar.iran.liara.run/public/3",
      "mobile": 7865,
      "email": "adelnouri0231@gmail.com",
      "job": "کارمندd",
      "group": "4",
      "id": 5
    }
  ],
  "groups": [
    {
      "id": "1",
      "name": "همکار"
    },
    {
      "id": "2",
      "name": "دوست"
    },
    {
      "id": "3",
      "name": "فامیل"
    },
    {
      "id": "4",
      "name": "سرویس"
    },
    {
      "id": "5",
      "name": "آشنا"
    }
  ]
}